terrascope/__init__.py
terrascope/cli/__init__.py
terrascope/cli/ts.py
terrascope/cli/commands/__init__.py
terrascope/cli/commands/algorithm.py
terrascope/cli/commands/algorithm_computation.py
terrascope/cli/commands/algorithm_config.py
terrascope/cli/commands/algorithm_version.py
terrascope/cli/commands/analysis.py
terrascope/cli/commands/analysis_computation.py
terrascope/cli/commands/analysis_config.py
terrascope/cli/commands/analysis_version.py
terrascope/cli/commands/aoi.py
terrascope/cli/commands/credit.py
terrascope/cli/commands/data.py
terrascope/cli/commands/environment.py
terrascope/cli/commands/imagery.py
terrascope/cli/commands/manifest.py
terrascope/cli/commands/permission.py
terrascope/cli/commands/tasks.py
terrascope/cli/commands/toi.py
terrascope/cli/commands/visualization.py
terrascope/cli/lib/__init__.py
terrascope/cli/lib/aliased_group.py
terrascope/cli/lib/utils.py
terrascope/cli/lib/workflow.py
terrascope/sdk/__init__.py
terrascope/sdk/terrascope_sdk.py
terrascope/sdk/api/__init__.py
terrascope/sdk/api/algorithm.py
terrascope/sdk/api/analysis.py
terrascope/sdk/api/aoi.py
terrascope/sdk/api/credit.py
terrascope/sdk/api/data.py
terrascope/sdk/api/filter.py
terrascope/sdk/api/order.py
terrascope/sdk/api/permission.py
terrascope/sdk/api/result.py
terrascope/sdk/api/tasking_order.py
terrascope/sdk/api/toi.py
terrascope/sdk/api/user.py
terrascope/sdk/api/visualization.py
terrascope/sdk/builder/__init__.py
terrascope/sdk/builder/algorithm.py
terrascope/sdk/builder/analysis.py
terrascope/sdk/builder/toi.py
terrascope/sdk/tools/__init__.py
terrascope/sdk/tools/io.py
terrascope/sdk/tools/sdk_support.py
terrascope_sdk-2025.10.82308.dist-info/licenses/LICENSE
tests/integration/test_algorithm.py
tests/integration/test_algorithm_builder.py
tests/integration/test_analysis.py
tests/integration/test_analysis_builder.py
tests/integration/test_aoi.py
tests/integration/test_credit.py
tests/integration/test_data.py
tests/integration/test_permission.py
tests/integration/test_result.py
terrascope_sdk-2025.10.82308.dist-info/METADATA
terrascope_sdk-2025.10.82308.dist-info/WHEEL
terrascope_sdk-2025.10.82308.dist-info/entry_points.txt
terrascope_sdk-2025.10.82308.dist-info/top_level.txt
terrascope_sdk-2025.10.82308.dist-info/RECORD
