Metadata-Version: 2.4
Name: terrascope-sdk
Version: 2025.10.82308
Summary: A software development kit for developing projects on TerraScope
Author: Orbital Insight
License: Copyright 2022 Orbital Insight, Inc.
Project-URL: Readme, https://terrascope.readme.io/docs
Keywords: Orbital Insight,OI,SDK,terrascope,terrascope-sdk,API,terrascope-api
Classifier: Programming Language :: Python :: 3
Classifier: License :: OSI Approved :: MIT License
Classifier: Operating System :: OS Independent
Requires-Python: >=3.10
License-File: LICENSE
Requires-Dist: grpcio-tools
Requires-Dist: pandas
Requires-Dist: numpy
Requires-Dist: wget
Requires-Dist: h3
Requires-Dist: geojson
Requires-Dist: chardet
Requires-Dist: click
Requires-Dist: pyyaml
Requires-Dist: geopandas
Requires-Dist: pytz
Requires-Dist: shapely
Requires-Dist: tabulate
Requires-Dist: timezonefinder
Requires-Dist: terrascope-api>=2025.10.82308
Requires-Dist: boto3
Provides-Extra: dev
Requires-Dist: pytest; extra == "dev"
Requires-Dist: pytest-asyncio; extra == "dev"
Requires-Dist: build; extra == "dev"
Requires-Dist: twine; extra == "dev"
Requires-Dist: flake8; extra == "dev"
Requires-Dist: grip; extra == "dev"
Dynamic: license-file
